{"chunk_definitions":[{"chunk_id":"c6u1tbgs0vptz","expansion_state":0,"options":[],"row":14,"row_count":1,"visible":true},{"chunk_id":"cqg71t8e9wesi","expansion_state":0,"options":[],"row":21,"row_count":1,"visible":true},{"chunk_id":"chpgukhdgqkof","expansion_state":0,"options":[],"row":33,"row_count":1,"visible":true},{"chunk_id":"cgu1vhglw1d5w","expansion_state":0,"options":[],"row":43,"row_count":1,"visible":true},{"chunk_id":"ckkf1txotk5cq","expansion_state":0,"options":[],"row":54,"row_count":1,"visible":true}],"doc_write_time":1676950137.4092}
